LICENSE.rst
MANIFEST.in
README.rst
requirements-optional.txt
requirements.txt
setup.cfg
setup.py
docs/api.rst
docs/builtins.rst
docs/conf.py
docs/demos.rst
docs/ffnet.rst
docs/gpu.rst
docs/index.rst
docs/installation.rst
docs/rnnet.rst
hessianfree/__init__.py
hessianfree/dataplotter.py
hessianfree/demos.py
hessianfree/ffnet.py
hessianfree/loss_funcs.py
hessianfree/nonlinearities.py
hessianfree/optimizers.py
hessianfree/rnnet.py
hessianfree/test.py
hessianfree/version.py
hessianfree.egg-info/PKG-INFO
hessianfree.egg-info/SOURCES.txt
hessianfree.egg-info/dependency_links.txt
hessianfree.egg-info/top_level.txt
hessianfree/gpu/__init__.py
hessianfree/gpu/kernel_wrappers.py
hessianfree/gpu/kernels.cu
hessianfree/gpu/profiling.py
hessianfree/tests/__init__.py
hessianfree/tests/test_demos.py
hessianfree/tests/test_ffnet.py
hessianfree/tests/test_gpu.py
hessianfree/tests/test_optimizers.py
hessianfree/tests/test_rnnet.py