Metadata-Version: 1.1
Name: hessianfree
Version: 0.4.0
Summary: Hessian-free optimization for deep networks
Home-page: https://github.com/drasmuss/hessianfree
Author: Daniel Rasmussen
Author-email: daniel.rasmussen@appliedbrainresearch.com
License: BSD
Download-URL: https://github.com/drasmuss/hessianfree/tarball/0.4.0
Keywords: neural network,hessian free,deep learning
Platform: UNKNOWN
Classifier: Development Status :: 4 - Beta
Classifier: Intended Audience :: Science/Research
Classifier: License :: OSI Approved :: BSD License
Classifier: Operating System :: Microsoft :: Windows
Classifier: Operating System :: Unix
Classifier: Programming Language :: Python
Classifier: Programming Language :: Python :: 2.7
Classifier: Programming Language :: Python :: 3.5
Classifier: Topic :: Scientific/Engineering
